a_pandas_ex_to_dict/LICENSE
a_pandas_ex_to_dict/README.MD
a_pandas_ex_to_dict/__init__.py
a_pandas_ex_to_dict/requirements.txt
a_pandas_ex_to_dict/thirdparty.json
a_pandas_ex_to_dict-0.10.dist-info/LICENSE.rst
a_pandas_ex_to_dict-0.10.dist-info/METADATA
a_pandas_ex_to_dict-0.10.dist-info/WHEEL
a_pandas_ex_to_dict-0.10.dist-info/top_level.txt
a_pandas_ex_to_dict-0.10.dist-info/RECORD
